lsoft_docker/__init__.py
lsoft_docker/presets/__init__.py
lsoft_docker-1.0.0.dist-info/METADATA
lsoft_docker-1.0.0.dist-info/WHEEL
lsoft_docker-1.0.0.dist-info/RECORD
