Metadata-Version: 2.1
Name: lsoft-docker
Version: 1.0.0
Summary: high level docker functions
License: MIT
Author: Marco Bartel
Author-email: bartel@electronic-shop.lu
Requires-Python: >=3.12,<4.0
Classifier: License :: OSI Approved :: MIT License
Classifier: Programming Language :: Python :: 3
Requires-Dist: docker (>=7.1.0,<8.0.0)
Requires-Dist: pydantic (>=2.9.1,<3.0.0)
Requires-Dist: pydash
